{
  "project_info": {
    "project_number": "833582821897",
    "project_id": "impactly-284df",
    "storage_bucket": "impactly-284df.firebasestorage.app"
  },
  "client": [
    {
      "client_info": {
        "mobilesdk_app_id": "1:833582821897:android:f00a7cf5166ab4c4473ed8",
        "android_client_info": {
          "package_name": "com.example.impactly_new"
        }
      },
      "oauth_client": [],
      "api_key": [
        {
          "current_key": "AIzaSyCmXbS8BRWQkM9vdT4pLvBmoh_c6dHxepQ"
        }
      ],
      "services": {
        "appinvite_service": {
          "other_platform_oauth_client": []
        }
      }
    }
  ],
  "configuration_version": "1"
}